inincompatibility/__init__.py
inincompatibility/__main__.py
inincompatibility/iclient.py
inincompatibility/iserver.py
inincompatibility-0.0.8.dist-info/LICENSE
inincompatibility-0.0.8.dist-info/METADATA
inincompatibility-0.0.8.dist-info/WHEEL
inincompatibility-0.0.8.dist-info/top_level.txt
inincompatibility-0.0.8.dist-info/RECORD
