Metadata-Version: 2.1
Name: inincompatibility
Version: 0.0.8
Summary: A dependency-free, code-less socket-based solution for resolving environment incompatibilities
Author-email: userElaina <userelaina@pm.me>
Maintainer-email: userElaina <userelaina@pm.me>
License: MIT License
Project-URL: Homepage, https://github.com/userElaina/inincompatibility
Project-URL: Bug Reports, https://github.com/userElaina/inincompatibility/issues
Project-URL: Source, https://github.com/userElaina/inincompatibility
Keywords: compatibility,incompatibility,socket
Classifier: License :: OSI Approved :: MIT License
Classifier: Programming Language :: Python :: 3
Requires-Python: >=3.7
License-File: LICENSE
